june/__init__.py
june/june.py
june_py-0.1.11.dist-info/LICENSE
june_py-0.1.11.dist-info/METADATA
june_py-0.1.11.dist-info/WHEEL
june_py-0.1.11.dist-info/top_level.txt
june_py-0.1.11.dist-info/RECORD
