Metadata-Version: 2.1
Name: june-py
Version: 0.1.11
Summary: A python API wrapper for June
Home-page: https://github.com/energieid/june
Author: EnergieID.be
Author-email: jan@energieid.be
License: MIT
Keywords: june data monitoring api
Classifier: Development Status :: 3 - Alpha
Classifier: Intended Audience :: Developers
Classifier: Topic :: Scientific/Engineering
Classifier: License :: OSI Approved :: MIT License
Classifier: Programming Language :: Python :: 3
Classifier: Programming Language :: Python :: 3.2
Classifier: Programming Language :: Python :: 3.3
Classifier: Programming Language :: Python :: 3.4
Classifier: Programming Language :: Python :: 3.5
Classifier: Programming Language :: Python :: 3.6
License-File: LICENSE
Requires-Dist: requests
Requires-Dist: pytz
Requires-Dist: python-dateutil
